pg_prefix_search/__init__.py
pg_prefix_search/migrations/0001_initial.py
pg_prefix_search/models.py
pg_prefix_search/scripts/__init__.py
pg_prefix_search/scripts/makemigrations.py
pg_prefix_search/scripts/mock_settings.py
pg_prefix_search/search.py
pg_prefix_search-0.1.0.dist-info/WHEEL
pg_prefix_search-0.1.0.dist-info/METADATA
pg_prefix_search-0.1.0.dist-info/RECORD
