Metadata-Version: 2.1
Name: pg-prefix-search
Version: 0.1.0
Summary: Text search by word fragments using Postgres-specific indices.
Author: Szymon Sobczak
Author-email: szymon@solvbot.pl
Requires-Python: >=3.10,<4.0
Classifier: Programming Language :: Python :: 3
Classifier: Programming Language :: Python :: 3.10
Requires-Dist: Django (>=3.2,<4.0)
Requires-Dist: Unidecode (>=1.3.4,<2.0.0)
